Workbook

Sheet Dados iniciais
A2: COD_CNAE2.0 | B2: Atividade | C2: 36 horas ou menos | D2: 37 a 40 horas | E2: 41 horas ou mais | F2: Total | G2: % afetado
A3: 48080 | B3: =VLOOKUP(A3,Planilha1!$1:$1048576,2,FALSE) -> Supermercado e hipermercado | C3: 1236.2223 | D3: 1266.4276 | E3: 7100.6128 | F3: =SUM(C3:E3) -> 9603.2627 | G3: =E3/F3 -> 0.73939587
A4: 48030 | B4: =VLOOKUP(A4,Planilha1!$1:$1048576,2,FALSE) -> Comércio de produtos alimentícios, bebidas e fumo | C4: 1698.2788 | D4: 2031.4447 | E4: 6484.4235 | F4: =SUM(C4:E4) -> 10214.147 | G4: =E4/F4 -> 0.63484729
A5: 56011 | B5: =VLOOKUP(A5,Planilha1!$1:$1048576,2,FALSE) -> Restaurantes e outros estabelecimentos de serviços de alimentação e bebidas | C5: 4349.303 | D5: 1681.6729 | E5: 6072.1376 | F5: =SUM(C5:E5) -> 12103.113 | G5: =E5/F5 -> 0.50170046
A6: 41000 | B6: =VLOOKUP(A6,Planilha1!$1:$1048576,2,FALSE) -> Construção de edifícios | C6: 3193.2264 | D6: 5476.7693 | E6: 4993.0228 | F6: =SUM(C6:E6) -> 13663.018 | G6: =E6/F6 -> 0.36544068
A7: 48042 | B7: =VLOOKUP(A7,Planilha1!$1:$1048576,2,FALSE) -> Comércio de artigos do vestuário, complementos, calçados e artigos de viagem | C7: 1215.1825 | D7: 1527.51 | E7: 4336.6854 | F7: =SUM(C7:E7) -> 7079.3778 | G7: =E7/F7 -> 0.61258002
A8: 45020 | B8: =VLOOKUP(A8,Planilha1!$1:$1048576,2,FALSE) -> Manutenção e reparação de veículos automotores | C8: 1339.7347 | D8: 1385.0138 | E8: 3909.1199 | F8: =SUM(C8:E8) -> 6633.8685 | G8: =E8/F8 -> 0.58926702
A9: 49030 | B9: =VLOOKUP(A9,Planilha1!$1:$1048576,2,FALSE) -> Transporte rodoviário de passageiros | C9: 1353.276 | D9: 2447.9433 | E9: 3462.9537 | F9: =SUM(C9:E9) -> 7264.173 | G9: =E9/F9 -> 0.47671686
A10: 48050 | B10: =VLOOKUP(A10,Planilha1!$1:$1048576,2,FALSE) -> Comércio de madeira, material de construção, ferragens e ferramentas | C10: 330.24556 | D10: 1150.8273 | E10: 3441.4973 | F10: =SUM(C10:E10) -> 4922.5701 | G10: =E10/F10 -> 0.69912611
A11: 1201 | B11: =VLOOKUP(A11,Planilha1!$1:$1048576,2,FALSE) -> Criação de bovinos | C11: 3204.6237 | D11: 1210.9875 | E11: 3311.3665 | F11: =SUM(C11:E11) -> 7726.9778 | G11: =E11/F11 -> 0.42854614
A12: 48071 | B12: =VLOOKUP(A12,Planilha1!$1:$1048576,2,FALSE) -> Comércio de produtos farmaceuticos, médicos, ortopédicos, odontológicos e de cosméticos e perfumaria | C12: 2140.1407 | D12: 899.65289 | E12: 3162.6617 | F12: =SUM(C12:E12) -> 6202.4553 | G12: =E12/F12 -> 0.5099048
A13: 97000 | B13: =VLOOKUP(A13,Planilha1!$1:$1048576,2,FALSE) -> Serviços domésticos | C13: 7538.5912 | D13: 4016.5572 | E13: 3138.7933 | F13: =SUM(C13:E13) -> 14693.942 | G13: =E13/F13 -> 0.21361139
A14: 84014 | B14: =VLOOKUP(A14,Planilha1!$1:$1048576,2,FALSE) -> Defesa | C14: 999.36159 | D14: 1607.5822 | E14: 2954.9959 | F14: =SUM(C14:E14) -> 5561.9396 | G14: =E14/F14 -> 0.53128873
... A141: 94099 | B141: =VLOOKUP(A141,Planilha1!$1:$1048576,2,FALSE) -> Outras atividades associativas não especificadas anteriormente | C141: 357.72746 | D141: 294.35259 | E141: 0 | F141: =SUM(C141:E141) -> 652.08005 | G141: =E141/F141 -> 0

Sheet Planilha1
A1: COD | B1: Atividade
B2: AGRICULTURA, PECUÁRIA, CAÇA E SERVIÇOS RELACIONADOS
A3: 1101 | B3: Cultivo de arroz
A4: 1102 | B4: Cultivo de milho
A5: 1103 | B5: Cultivo de outros cereais
A6: 1104 | B6: Cultivo de algodão
A7: 1105 | B7: Cultivo de cana-de-açúcar
A8: 1106 | B8: Cultivo de fumo
A9: 1107 | B9: Cultivo de soja
A10: 1108 | B10: Cultivo de mandioca
A11: 1109 | B11: Cultivo de outras lavouras temporárias não especificadas anteriormente
A12: 1110 | B12: Horticultura
A13: 1111 | B13: Cultivo de flores e plantas ornamentais
A14: 1112 | B14: Cultivo de frutas cítricas
... A34: 1999 | B34: Agropecuária
B35: PRODUÇÃO FLORESTAL
A36: 2000 | B36: Produção florestal
B37: PESCA E AQÜICULTURA
A38: 3001 | B38: Pesca
A39: 3002 | B39: Aqüicultura
B40: INDÚSTRIAS EXTRATIVAS
B41: EXTRAÇÃO DE CARVÃO MINERAL
A42: 5000 | B42: Extração de carvão mineral
B43: EXTRAÇÃO DE PETRÓLEO E GÁS NATURAL
A44: 6000 | B44: Extração de petróleo e gás natural
B45: EXTRAÇÃO DE MINERAIS METÁLICOS
A46: 7001 | B46: Extração de minérios de metais preciosos
A47: 7002 | B47: Extração de minerais metálicos não especificados anteriormente
B48: EXTRAÇÃO DE MINERAIS NÃO-METÁLICOS
A49: 8001 | B49: Extração de pedras, areia e argila
A50: 8002 | B50: Extração de gemas (pedras preciosas e semi-preciosas)
A51: 8009 | B51: Extração de minerais não metálicos não especificados anteriormente
B52: ATIVIDADES DE APOIO À EXTRAÇÃO DE MINERAIS
A53: 9000 | B53: Atividades de apoio à extração de minerais
B54: INDÚSTRIAS DE TRANSFORMAÇÃO
B55: FABRICAÇÃO DE PRODUTOS ALIMENTÍCIOS
A56: 10010 | B56: Abate e fabricação de produtos de carne e pescado
A57: 10021 | B57: Fabricação de conservas de frutas, legumes e outros vegetais
A58: 10022 | B58: Fabricação de óleos vegetais e gorduras vegetais e animais
A59: 10030 | B59: Laticínios
A60: 10091 | B60: Moagem, fabricação de produtos amiláceos e de alimentos para animais
A61: 10092 | B61: Fabricação e refino do açúcar
A62: 10093 | B62: Torrefação e moagem de café
A63: 10099 | B63: Fabricação de outros produtos alimentícios
B64: FABRICAÇÃO DE BEBIDAS
A65: 11000 | B65: Fabricação de bebidas
B66: FABRICAÇÃO DE PRODUTOS DO FUMO
A67: 12000 | B67: Processamento industrial e fabricação de produtos do fumo
B68: FABRICAÇÃO DE PRODUTOS TÊXTEIS
A69: 13001 | B69: Preparação de fibras, fiação e tecelagem
A70: 13002 | B70: Fabricação de artefatos têxteis, exceto vestuário
B71: CONFECÇÃO DE ARTIGOS DO VESTUÁRIO E ACESSÓRIOS
A72: 14001 | B72: Confecção de artigos do vestuário e acessórios, exceto sob medida
A73: 14002 | B73: Confecção, sob medida, de artigos do vestuário
B74: PREPARAÇÃO DE COUROS E FABRICAÇÃO DE ARTEFATOS DE COURO, ARTIGOS DE VIAGEM E CALÇADOS
A75: 15011 | B75: Curtimento e outras preparações de couro
A76: 15012 | B76: Fabricação de artigos de viagem e de artefatos diversos de couro
A77: 15020 | B77: Fabricação de calçados e partes para calçados, de qualquer material
B78: FABRICAÇÃO DE PRODUTOS DE MADEIRA
A79: 16001 | B79: Serrarias
A80: 16002 | B80: Fabricação de produtos de madeira, cortiça e material trançado, exceto móveis
B81: FABRICAÇÃO DE CELULOSE, PAPEL E PRODUTOS DE PAPEL
A82: 17001 | B82: Fabricação de celulose, papel, cartolina e papel-cartão
A83: 17002 | B83: Fabricação de embalagens e de produtos diversos de papel, cartolina, papel-cartão e papelão ondulado
B84: IMPRESSÃO E REPRODUÇÃO DE GRAVAÇÕES
A85: 18000 | B85: Impressão e reprodução de gravações
B86: FABRICAÇÃO DE COQUE; PRODUTOS DERIVADOS DE PETRÓLEO E DE BIOCOMBUSTÍVEIS
A87: 19010 | B87: Coquerias
A88: 19020 | B88: Fabricação de produtos derivados do petróleo
A89: 19030 | B89: Produção de biocombustíveis
B90: FABRICAÇÃO DE PRODUTOS QUÍMICOS
A91: 20010 | B91: Fabricação de tintas, vernizes, esmaltes, lacas e produtos afins
A92: 20020 | B92: Fabricação de sabões, detergentes, produtos de limpeza, cosméticos, produtos de perfumaria e de higiene pessoal
A93: 20090 | B93: Fabricação de outros produtos químicos não especificados anteriormente
B94: FABRICAÇÃO DE PRODUTOS FARMOQUÍMICOS E FARMACÊUTICOS
A95: 21000 | B95: Fabricação de produtos farmoquimicos e farmacêuticos
B96: FABRICAÇÃO DE PRODUTOS DE BORRACHA E DE MATERIAL PLÁSTICO
A97: 22010 | B97: Fabricação de produtos de borracha
A98: 22020 | B98: Fabricação de produtos de material plástico
B99: FABRICAÇÃO DE PRODUTOS DE MINERAIS NÃO-METÁLICOS
A100: 23010 | B100: Fabricação de vidro e produtos de vidro
A101: 23091 | B101: Fabricação de produtos cerâmicos
A102: 23099 | B102: Fabricação de outros produtos de minerais não-metálicos não especificados anteriormente
B103: METALURGIA
A104: 24001 | B104: Fabricação de produtos siderúrgicos
A105: 24002 | B105: Metalurgia dos metais não-ferrosos
A106: 24003 | B106: Fundição
B107: FABRICAÇÃO DE PRODUTOS DE METAL, EXCETO MÁQUINAS E EQUIPAMENTOS
A108: 25001 | B108: Fabricação de produtos de metal, exceto máquinas e equipamentos
A109: 25002 | B109: Forjaria, estamparia, metalurgia do pó e serviços de tratamento de metais
B110: FABRICAÇÃO DE EQUIPAMENTOS DE INFORMÁTICA, PRODUTOS ELETRÔNICOS E ÓPTICOS
A111: 26010 | B111: Fabricação de componentes eletrônicos
A112: 26020 | B112: Fabricação de equipamentos de informática e periféricos
A113: 26030 | B113: Fabricação de equipamentos de comunicação e de aparelhos de recepção, reprodução, gravação e amplificação de áudio e vídeo
A114: 26041 | B114: Fabricação de aparelhos e instrumentos de medida, teste e controle; cronômetros e relógios e de aparelhos eletromédicos e eletroterapêuticos
A115: 26042 | B115: Fabricação de equipamentos e instrumentos ópticos, fotográficos e cinematográficos e de mídias virgens, magnéticas e ópticas
B116: FABRICAÇÃO DE MÁQUINAS, APARELHOS E MATERIAIS ELÉTRICOS
A117: 27010 | B117: Fabricação de eletrodomesticos
A118: 27090 | B118: Fabricação de máquinas, aparelhos e materiais elétricos diversos, exceto eletrodomesticos
B119: FABRICAÇÃO DE MÁQUINAS E EQUIPAMENTOS
...

Sheet Planilha3
C2: VD4035 >= 37 & VD4035 <= 40TRUE
B3: 1102 | C3: 159.71786
B4: 1107 | C4: 130.69199
B5: 1108 | C5: 171.63484
B6: 1109 | C6: 23.443549
B7: 1110 | C7: 886.59685
B8: 1112 | C8: 97.412561
B9: 1114 | C9: 7.232921
B10: 1116 | C10: 1529.0325
B11: 1117 | C11: 134.47757
B12: 1201 | C12: 1210.9875
B13: 1202 | C13: 0
B14: 1204 | C14: 0
... B141: 97000 | C141: 4016.5572

Sheet Planilha4
C2: VD4035 >= 41TRUE
B3: 1102 | C3: 149.18188
B4: 1107 | C4: 316.77251
B5: 1108 | C5: 465.89126
B6: 1109 | C6: 357.6619
B7: 1110 | C7: 181.38862
B8: 1112 | C8: 0
B9: 1114 | C9: 0
B10: 1116 | C10: 1285.8082
B11: 1117 | C11: 658.67081
B12: 1201 | C12: 3311.3665
B13: 1202 | C13: 59.47505
B14: 1204 | C14: 148.19057
... B141: 97000 | C141: 3138.7933
